refclone/__init__.py
refclone-0.1.dist-info/METADATA
refclone-0.1.dist-info/RECORD
refclone-0.1.dist-info/WHEEL
refclone-0.1.dist-info/entry_points.txt
refclone-0.1.dist-info/top_level.txt
