Metadata-Version: 2.1
Name: refclone
Version: 0.1
Summary: A wrapper for "git clone" that keeps git repo directories organized
Home-page: https://bitbucket.org/alcm-b/refclone
Author: Egor Berdnikov
Author-email: egor.berdnikov@gmail.com
License: MIT
Platform: POSIX
Classifier: Development Status :: 4 - Beta
Classifier: Environment :: Console
Classifier: Topic :: Software Development :: Version Control :: Git
Classifier: Topic :: Utilities
Classifier: Programming Language :: Python :: 3
Classifier: License :: OSI Approved :: MIT License
Classifier: Operating System :: OS Independent
